jupyterlab_macaulay2/__init__.py
jupyterlab_macaulay2/_version.py
jupyterlab_macaulay2-0.2.2.data/data/share/jupyter/labextensions/jupyterlab-macaulay2/package.json
jupyterlab_macaulay2-0.2.2.data/data/share/jupyter/labextensions/jupyterlab-macaulay2/static/220.b20e13eec5389a82790d.js
jupyterlab_macaulay2-0.2.2.data/data/share/jupyter/labextensions/jupyterlab-macaulay2/static/57.24da7a4f53017a85160d.js
jupyterlab_macaulay2-0.2.2.data/data/share/jupyter/labextensions/jupyterlab-macaulay2/static/679.b2c3c587112088e8ae95.js
jupyterlab_macaulay2-0.2.2.data/data/share/jupyter/labextensions/jupyterlab-macaulay2/static/728.ac0b7099b1f4c6739ffa.js
jupyterlab_macaulay2-0.2.2.data/data/share/jupyter/labextensions/jupyterlab-macaulay2/static/851.38fda7cb0d97d240c3df.js
jupyterlab_macaulay2-0.2.2.data/data/share/jupyter/labextensions/jupyterlab-macaulay2/static/remoteEntry.f539b3650653d99afe75.js
jupyterlab_macaulay2-0.2.2.data/data/share/jupyter/labextensions/jupyterlab-macaulay2/static/style.js
jupyterlab_macaulay2-0.2.2.data/data/share/jupyter/labextensions/jupyterlab-macaulay2/static/third-party-licenses.json
jupyterlab_macaulay2-0.2.2.data/data/share/jupyter/labextensions/jupyterlab-macaulay2/install.json
jupyterlab_macaulay2-0.2.2.dist-info/METADATA
jupyterlab_macaulay2-0.2.2.dist-info/WHEEL
jupyterlab_macaulay2-0.2.2.dist-info/licenses/LICENSE
jupyterlab_macaulay2-0.2.2.dist-info/RECORD
