Metadata-Version: 2.4
Name: jupyterlab_macaulay2
Version: 0.2.2
Summary: CodeMirror-based syntax highlighting for Macaulay2 in Jupyter code cells
Project-URL: Homepage, https://github.com/d-torrance/jupyterlab-macaulay2
Project-URL: Bug Tracker, https://github.com/d-torrance/jupyterlab-macaulay2/issues
Project-URL: Repository, https://github.com/d-torrance/jupyterlab-macaulay2.git
Author-email: Doug Torrance <dtorrance@piedmont.edu>
License: BSD 3-Clause License
License-File: LICENSE
Keywords: jupyter,jupyterlab,jupyterlab-extension
Classifier: Framework :: Jupyter
Classifier: Framework :: Jupyter :: JupyterLab
Classifier: Framework :: Jupyter :: JupyterLab :: 4
Classifier: Framework :: Jupyter :: JupyterLab :: Extensions
Classifier: Framework :: Jupyter :: JupyterLab :: Extensions :: Prebuilt
Classifier: License :: OSI Approved :: BSD License
Classifier: Programming Language :: Python
Classifier: Programming Language :: Python :: 3
Classifier: Programming Language :: Python :: 3.9
Classifier: Programming Language :: Python :: 3.10
Classifier: Programming Language :: Python :: 3.11
Classifier: Programming Language :: Python :: 3.12
Classifier: Programming Language :: Python :: 3.13
Requires-Python: >=3.9
